src/counter.v
// Neander Program Counter

module counter (
    i_clk,
    i_rst,
    i_preload,
    i_preload_s,
    i_inc,
    
    o_PC
);
    input i_clk;
    input i_rst;
    input [7:0] i_preload;
    input i_preload_s;
    input i_inc;

    output [7:0] o_PC;

    reg [7:0] internal_PC;

    always @(posedge i_clk) begin
        if(!i_rst) begin
            if(i_inc) 
                internal_PC <= (i_preload_s ? i_preload : (internal_PC + 1));
            
        end
        else
            internal_PC <= 8'b0;
    end

    assign o_PC = internal_PC;
    
endmodule

src/ULA.v
// Unidadade Lógica Aritmética

// 0000	NOP	Nenhuma operação
// 0001	STA end	Armazena acumulador no endereço “end” da memória
// 0010	LDA end	Carrega o acumulador com o conteúdo do endereço “end” da memória
// 0011	ADD end	Soma o conteúdo do endereço “end” da memória ao acumulador
// 0100	OR end	Efetua operação lógica “OU” do conteúdo do endereço “end” da memória ao acumulador
// 0101	AND end	Efetua operação lógica “E” do conteúdo do endereço “end” da memória ao acumulador
// 0110	NOT	Inverte todos os bits do acumulador

// Pegamos os 3 LSBs e utilizamos para o mux da ULA, simplificando o decodificador de instrução

module ULA (
    i_A, i_B, i_SEL, o_OUT, o_ZERO, o_NEG
);

    localparam ADD = 3'b011;
    localparam OR  = 3'b100;
    localparam AND = 3'b101;
    localparam NOT = 3'b110;

    input wire [7:0] i_A;
    input wire [7:0] i_B;
    input wire [2:0] i_SEL;

    output reg [7:0] o_OUT;
    output reg o_ZERO;
    output reg o_NEG;
    
    always @(i_A, i_B, i_SEL) begin
        case (i_SEL)
            ADD: o_OUT = i_A + i_B; // ADD
            OR:  o_OUT = i_A | i_B; // OR
            AND: o_OUT = i_A & i_B; // AND
            NOT: o_OUT = ~i_B; // NOT

            default: o_OUT = i_B; // ELSE
        endcase

        o_ZERO = o_OUT == 0;
        o_NEG  = o_OUT[7];
    end
endmodule

src/neander.v
module neander (
    i_clk,
    i_rst
);

    localparam OP_NOP = 8'b00000000;
    localparam OP_STA = 8'b00000001;
    localparam OP_LDA = 8'b00000010;
    localparam OP_ADD = 8'b00000011;
    localparam OP_OR  = 8'b00000100;
    localparam OP_AND = 8'b00000101;
    localparam OP_NOT = 8'b00000110;

    localparam OP_JMP = 8'b00001000;
    localparam OP_JN  = 8'b00001001;
    localparam OP_JZ  = 8'b00001010;
    localparam OP_HLT = 8'b00001111;

    localparam ULA_ADD = 3'b011;
    localparam ULA_OR  = 3'b100;
    localparam ULA_AND = 3'b101;
    localparam ULA_NOT = 3'b110;

    input i_clk;
    input i_rst;

    reg [7:0] ACC ;
    reg [2:0] ULA_SEL;
    wire [7:0] ULA_OUT;

    wire [7:0] ULA_Y;
    wire ULA_Z;
    wire ULA_N;

    reg cargaAC;
    reg cargaNZ;
    reg cargaREM;
    reg cargaRDM;
    reg cargaRI;
    reg memRead;
    reg memWrite;

    reg [7:0] RI;
    reg [7:0] REM;
    reg [7:0] RDM;
    reg SEL;
    reg N;
    reg Z;

    reg [2:0] STATE;

    assign ULA_Y = RDM;


    // /* verilator public */
    ULA ula(.i_A(ACC), .i_B(ULA_Y), .i_SEL(ULA_SEL), .o_OUT(ULA_OUT), .o_ZERO(ULA_Z), .o_NEG(ULA_N));


    reg [7:0] valorPC;
    reg [7:0] cargaPC_val;
    reg cargaPC;
    reg incrementaPC;

    wire isJump;
    assign isJump = RI[3];

    counter PC(.i_clk(i_clk), .i_rst(i_rst), .i_preload(cargaPC_val), .i_preload_s(cargaPC), .i_inc(incrementaPC), .o_PC(valorPC));


    reg [7:0] memory [0:255];

    always @(posedge i_clk ) begin
        if (memWrite) begin
            memory[REM] <= RDM;
        end
    end

    always @(posedge i_clk ) begin
        if(memRead) begin
            RDM <= memory[REM];
        end
    end

    always @(posedge i_clk) begin
        if(cargaAC) begin
            ACC <= ULA_OUT;
        end

        if(cargaNZ) begin
            Z <= ULA_Z;
            N <= ULA_N;
        end

        if(cargaPC) begin
            cargaPC_val <= RDM;
        end

        if(SEL) begin
            if (cargaREM) begin
                REM <= RDM;
            end
        end else begin
            if (cargaREM) begin
                REM <= valorPC;
            end
        end

        if (cargaRDM) begin
            RDM <= ACC;
        end

        if (cargaRI) begin
            RI <= RDM;
        end

        case (STATE)
            3'd0: begin
                STATE <= 1;
            end
            3'd1: begin
                STATE <= 2;
            end
            3'd2: begin
                STATE <= 3;
            end
            3'd3: begin
                if(RI == OP_NOT) begin
                    STATE <= 0;
                end else begin
                    if(((RI == OP_JN) && ~N) | ((RI == OP_JZ) &&  ~Z)) begin
                        STATE <= 0;
                    end else begin
                        STATE <= 4;
                    end
                end
            end
            3'd4: begin
                STATE <= 5;
            end
            3'd5: begin
                if (isJump) begin
                    STATE <= 0;
                end else begin
                    STATE <= 6;
                end
            end
            3'd6: begin
                STATE <= 7;
            end
            3'd7: begin
                STATE <= 0;
            end
        endcase
    end

    always @(STATE) begin
        case (STATE)
            3'd0: begin
                incrementaPC = 0;
                cargaAC = 0;
                cargaNZ = 0;
                cargaPC = 0;
                SEL = 0;
                memWrite = 0;
                memRead = 0;
                cargaREM = 1;
                //STATE <= 1;
            end
            3'd1: begin
                memRead = 1;
                incrementaPC = 1;
                cargaREM = 0;
                //STATE <= 2;
            end
            3'd2: begin
                memRead = 0;
                incrementaPC = 0;
                cargaRI = 1;
                //STATE <= 3;
            end
            3'd3: begin
                cargaRI = 0;
                if(RI == OP_NOT) begin
                    ULA_SEL = ULA_NOT;
                    cargaAC = 1;
                    cargaNZ = 1;
                    //STATE <= 0;
                end else begin
                    if(((RI == OP_JN) && ~N) | ((RI == OP_JZ) &&  ~Z)) begin
                        incrementaPC = 1;
                        //STATE <= 0;
                    end else begin
                        SEL = 0;
                        cargaREM = 1;
                        //STATE <= 4;
                    end
                end
            end
            3'd4: begin
                cargaREM = 0;
                memRead = 1;
                if (!isJump) begin
                    incrementaPC = 1;
                end
                //STATE <= 5;
            end
            3'd5: begin
                incrementaPC = 0;
                if(isJump) begin
                    cargaPC = 1;
                    //STATE <= 0;
                end else begin
                    SEL = 1;
                    cargaREM = 1;
                    //STATE <= 6;
                end
            end
            3'd6: begin
                cargaREM = 0;
                if(RI == OP_STA) begin
                    cargaRDM = 1;
                end else begin
                    memRead = 1;
                end
                //STATE <= 7;
            end
            3'd7: begin
                if(RI == OP_STA) begin
                    memWrite = 1;
                end else begin
                    cargaAC = 1;
                    cargaNZ = 1;
                    ULA_SEL = RI[2:0];
                end

                //STATE <= 0;
            end
        endcase
    end


endmodule

trace.vcd
$version Generated by VerilatedVcd $end
$date Mon Nov 29 21:37:38 2021
 $end
$timescale  10s $end

 $scope module TOP $end
  $var wire  1 ; i_clk $end
  $var wire  1 < i_rst $end
  $scope module neander $end
   $var wire  8 # ACC [7:0] $end
   $var wire  1 3 N $end
   $var wire  8 @ OP_ADD [7:0] $end
   $var wire  8 B OP_AND [7:0] $end
   $var wire  8 G OP_HLT [7:0] $end
   $var wire  8 D OP_JMP [7:0] $end
   $var wire  8 E OP_JN [7:0] $end
   $var wire  8 F OP_JZ [7:0] $end
   $var wire  8 ? OP_LDA [7:0] $end
   $var wire  8 = OP_NOP [7:0] $end
   $var wire  8 C OP_NOT [7:0] $end
   $var wire  8 A OP_OR [7:0] $end
   $var wire  8 > OP_STA [7:0] $end
   $var wire  8 & RDM [7:0] $end
   $var wire  8 1 REM [7:0] $end
   $var wire  8 0 RI [7:0] $end
   $var wire  1 2 SEL $end
   $var wire  3 5 STATE [2:0] $end
   $var wire  3 H ULA_ADD [2:0] $end
   $var wire  3 J ULA_AND [2:0] $end
   $var wire  1 ( ULA_N $end
   $var wire  3 K ULA_NOT [2:0] $end
   $var wire  3 I ULA_OR [2:0] $end
   $var wire  8 % ULA_OUT [7:0] $end
   $var wire  3 $ ULA_SEL [2:0] $end
   $var wire  8 & ULA_Y [7:0] $end
   $var wire  1 ' ULA_Z $end
   $var wire  1 4 Z $end
   $var wire  1 ) cargaAC $end
   $var wire  1 * cargaNZ $end
   $var wire  1 8 cargaPC $end
   $var wire  8 7 cargaPC_val [7:0] $end
   $var wire  1 , cargaRDM $end
   $var wire  1 + cargaREM $end
   $var wire  1 - cargaRI $end
   $var wire  1 ; i_clk $end
   $var wire  1 < i_rst $end
   $var wire  1 9 incrementaPC $end
   $var wire  1 : isJump $end
   $var wire  1 . memRead $end
   $var wire  1 / memWrite $end
   $var wire  8 6 valorPC [7:0] $end
   $scope module PC $end
    $var wire  1 ; i_clk $end
    $var wire  1 9 i_inc $end
    $var wire  8 7 i_preload [7:0] $end
    $var wire  1 8 i_preload_s $end
    $var wire  1 < i_rst $end
    $var wire  8 6 internal_PC [7:0] $end
    $var wire  8 6 o_PC [7:0] $end
   $upscope $end
   $scope module ula $end
    $var wire  3 H ADD [2:0] $end
    $var wire  3 J AND [2:0] $end
    $var wire  3 K NOT [2:0] $end
    $var wire  3 I OR [2:0] $end
    $var wire  8 # i_A [7:0] $end
    $var wire  8 & i_B [7:0] $end
    $var wire  3 $ i_SEL [2:0] $end
    $var wire  1 ( o_NEG $end
    $var wire  8 % o_OUT [7:0] $end
    $var wire  1 ' o_ZERO $end
   $upscope $end
  $upscope $end
 $upscope $end
$enddefinitions $end


#0
b00000000 #
b000 $
b00000000 %
b00000000 &
0'
0(
0)
0*
0+
0,
0-
0.
0/
b00000000 0
b00000000 1
02
03
04
b000 5
b00000000 6
b00000000 7
08
09
0:
0;
0<
b00000000 =
b00000001 >
b00000010 ?
b00000011 @
b00000100 A
b00000101 B
b00000110 C
b00001000 D
b00001001 E
b00001010 F
b00001111 G
b011 H
b100 I
b101 J
b110 K
#1
1'
1.
b001 5
19
#2
b00000010 %
b00000010 &
0'
1-
0.
b010 5
b00000001 6
09
#3
1+
0-
b00000010 0
b011 5
#4
0+
1.
b00000001 1
b100 5
19
#5
b10000000 %
b10000000 &
1(
1+
12
b101 5
b00000010 6
09
#6
0+
b10000000 1
b110 5
#7
b010 $
b00011000 %
b00011000 &
0(
1)
1*
b111 5
#8
b00011000 #
0)
0*
1+
0.
02
b000 5
#9
0+
1.
b00000010 1
b001 5
19
#10
b00000011 %
b00000011 &
1-
0.
b010 5
b00000011 6
09
#11
1+
0-
b00000011 0
b011 5
#12
0+
1.
b00000011 1
b100 5
19
#13
b10000001 %
b10000001 &
1(
1+
12
b101 5
b00000100 6
09
#14
0+
b10000001 1
b110 5
#15
b011 $
b00100001 %
b00001001 &
0(
1)
1*
b111 5
#16
b00100001 #
b00101010 %
0)
0*
1+
0.
02
b000 5
#17
0+
1.
b00000100 1
b001 5
19
#18
b00100010 %
b00000001 &
1-
0.
b010 5
b00000101 6
09
#19
1+
0-
b00000001 0
b011 5
#20
0+
1.
b00000101 1
b100 5
19
#21
b10100011 %
b10000010 &
1(
1+
12
b101 5
b00000110 6
09
#22
0+
1,
b10000010 1
b110 5
#23
b01000010 %
b00100001 &
0(
1/
b111 5
#24
1+
0.
0/
02
b000 5
#25
0+
1.
b00000110 1
b001 5
19
#26
1-
0.
b010 5
b00000111 6
09
#27
1+
0-
b00100001 0
b011 5
#28
0+
1.
b00000111 1
b100 5
19
#29
1+
12
b101 5
b00001000 6
09
#30
0+
b00100001 1
b110 5
#31
b001 $
b00100001 %
1)
1*
b111 5
#32
0)
0*
1+
0.
02
b000 5
#33
0+
1.
b00001000 1
b001 5
19
#34
1-
0.
b010 5
b00001001 6
09
#35
1+
0-
b011 5
#36
0+
1.
b00001001 1
b100 5
19
#37
1+
12
b101 5
b00001010 6
09
#38
0+
b00100001 1
b110 5
#39
1)
1*
b111 5
#40
0)
0*
1+
0.
02
b000 5
#41
0+
1.
b00001010 1
b001 5
19
#42
1-
0.
b010 5
b00001011 6
09
#43
1+
0-
b011 5
#44
0+
1.
b00001011 1
b100 5
19
#45
1+
12
b101 5
b00001100 6
09
#46
0+
b00100001 1
b110 5
#47
1)
1*
b111 5
#48
0)
0*
1+
0.
02
b000 5
#49
0+
1.
b00001100 1
b001 5
19
