src/counter.v
// Neander Program Counter

module counter (
    i_clk,
    i_rst,
    i_preload,
    i_preload_s,
    i_inc,
    
    o_PC
);
    input i_clk;
    input i_rst;
    input [7:0] i_preload;
    input i_preload_s;
    input i_inc;

    output [7:0] o_PC;

    reg [7:0] internal_PC;

    always @(posedge i_clk) begin
        if(!i_rst) begin
            if(i_inc) 
                internal_PC <= (i_preload_s ? i_preload : (internal_PC + 1));
            
        end
        else
            internal_PC <= 8'b0;
    end

    assign o_PC = internal_PC;
    
endmodule

src/ULA.v
// Unidadade Lógica Aritmética

// 0000	NOP	Nenhuma operação
// 0001	STA end	Armazena acumulador no endereço “end” da memória
// 0010	LDA end	Carrega o acumulador com o conteúdo do endereço “end” da memória
// 0011	ADD end	Soma o conteúdo do endereço “end” da memória ao acumulador
// 0100	OR end	Efetua operação lógica “OU” do conteúdo do endereço “end” da memória ao acumulador
// 0101	AND end	Efetua operação lógica “E” do conteúdo do endereço “end” da memória ao acumulador
// 0110	NOT	Inverte todos os bits do acumulador

// Pegamos os 3 LSBs e utilizamos para o mux da ULA, simplificando o decodificador de instrução

module ULA (
    i_A, i_B, i_SEL, o_OUT, o_ZERO, o_NEG
);

    localparam ADD = 3'b011;
    localparam OR  = 3'b100;
    localparam AND = 3'b101;
    localparam NOT = 3'b110;

    input wire [7:0] i_A;
    input wire [7:0] i_B;
    input wire [2:0] i_SEL;

    output reg [7:0] o_OUT;
    output reg o_ZERO;
    output reg o_NEG;
    
    always @(i_A, i_B, i_SEL) begin
        case (i_SEL)
            ADD: o_OUT = i_A + i_B; // ADD
            OR:  o_OUT = i_A | i_B; // OR
            AND: o_OUT = i_A & i_B; // AND
            NOT: o_OUT = ~i_A; // NOT

            default: o_OUT = i_B; // ELSE
        endcase

        o_ZERO = o_OUT == 0;
        o_NEG  = o_OUT[7];
    end
endmodule

src/neander.v
module neander (
    i_clk,
    i_rst
);

    localparam OP_NOP = 8'b00000000;
    localparam OP_STA = 8'b00000001;
    localparam OP_LDA = 8'b00000010;
    localparam OP_ADD = 8'b00000011;
    localparam OP_OR  = 8'b00000100;
    localparam OP_AND = 8'b00000101;
    localparam OP_NOT = 8'b00000110;

    localparam OP_JMP = 8'b00001000;
    localparam OP_JN  = 8'b00001001;
    localparam OP_JZ  = 8'b00001010;
    localparam OP_HLT = 8'b00001111;

    localparam ULA_ADD = 3'b011;
    localparam ULA_OR  = 3'b100;
    localparam ULA_AND = 3'b101;
    localparam ULA_NOT = 3'b110;

    input i_clk;
    input i_rst;

    reg [7:0] ACC;
    reg [2:0] ULA_SEL;
    wire [7:0] ULA_OUT;

    wire [7:0] ULA_Y;
    wire ULA_Z;
    wire ULA_N;

    reg cargaAC;
    reg cargaNZ;
    reg cargaREM;
    reg cargaRDM;
    reg cargaRI;
    reg memRead;
    reg memWrite;

    reg [7:0] RI;
    reg [7:0] REM;
    reg [7:0] RDM;
    reg SEL;
    reg N;
    reg Z;

    reg [2:0] STATE;

    assign ULA_Y = RDM;


    // /* verilator public */
    ULA ula(.i_A(ACC), .i_B(ULA_Y), .i_SEL(ULA_SEL), .o_OUT(ULA_OUT), .o_ZERO(ULA_Z), .o_NEG(ULA_N));


    reg [7:0] valorPC;
    wire [7:0] cargaPC_val;
    reg cargaPC;
    reg incrementaPC;

    assign cargaPC_val = RDM;

    counter PC(.i_clk(i_clk), .i_rst(i_rst), .i_preload(cargaPC_val), .i_preload_s(cargaPC), .i_inc(incrementaPC), .o_PC(valorPC));


    reg [7:0] memory [0:255];

    always @(posedge i_clk ) begin
        if (memWrite) begin
            memory[REM] <= RDM;
        end
    end

    always @(posedge i_clk ) begin
        if(memRead) begin
            RDM <= memory[REM];
        end
    end

    always @(posedge i_clk) begin
        if(cargaAC) begin
            ACC <= ULA_OUT;
        end

        if(cargaNZ) begin
            Z <= ULA_Z;
            N <= ULA_N;
        end

        if(SEL) begin
            if (cargaREM) begin
                REM <= RDM;
            end
        end else begin
            if (cargaREM) begin
                REM <= valorPC;
            end
        end

        if (cargaRDM) begin
            RDM <= ACC;
        end

        if (cargaRI) begin
            RI <= RDM;
        end

        if (!i_rst) begin

            case (STATE)
                3'd0: begin
                    STATE <= 1;
                end
                3'd1: begin
                    STATE <= 2;
                end
                3'd2: begin
                    STATE <= 3;
                end
                3'd3: begin
                    if(RI == OP_NOT) begin
                        STATE <= 0;
                    end else begin
                        if(((RI == OP_JN) && ~N) | ((RI == OP_JZ) &&  ~Z) | RI == OP_HLT) begin
                            STATE <= 0;
                        end else begin
                            STATE <= 4;
                        end
                    end
                end
                3'd4: begin
                    STATE <= 5;
                end
                3'd5: begin
                    if ((RI == OP_JMP) | (RI == OP_JN) | (RI == OP_JZ)) begin
                        STATE <= 0;
                    end else begin
                        STATE <= 6;
                    end
                end
                3'd6: begin
                    STATE <= 7;
                end
                3'd7: begin
                    STATE <= 0;
                end
            endcase
        end else begin
            STATE <= 0;
        end
    end

    always @(STATE) begin
        case (STATE)
            3'd0: begin
                incrementaPC = 0;
                cargaAC = 0;
                cargaNZ = 0;
                cargaPC = 0;
                SEL = 0;
                memWrite = 0;
                memRead = 0;
                cargaREM = 1;
                //STATE <= 1;
            end
            3'd1: begin
                memRead = 1;
                incrementaPC = 1;
                cargaREM = 0;
                //STATE <= 2;
            end
            3'd2: begin
                memRead = 0;
                incrementaPC = 0;
                cargaRI = 1;
                //STATE <= 3;
            end
            3'd3: begin
                cargaRI = 0;
                if(RI == OP_NOT) begin
                    ULA_SEL = ULA_NOT;
                    cargaAC = 1;
                    cargaNZ = 1;
                    //STATE <= 0;
                end else begin
                    if(((RI == OP_JN) && ~N) | ((RI == OP_JZ) &&  ~Z)) begin
                        incrementaPC = 1;
                        //STATE <= 0;
                    end else begin
                        SEL = 0;
                        cargaREM = 1;
                        //STATE <= 4;
                    end
                end
            end
            3'd4: begin
                cargaREM = 0;
                memRead = 1;
                if ((RI == OP_JMP) | (RI == OP_JN) | (RI == OP_JZ)) begin
                    incrementaPC = 0;
                end else begin
                    incrementaPC = 1;
                end
                //STATE <= 5;
            end
            3'd5: begin
                incrementaPC = 0;
                if((RI == OP_JMP) | (RI == OP_JN) | (RI == OP_JZ)) begin
                    cargaPC = 1;
                    //STATE <= 0;
                end else begin
                    SEL = 1;
                    cargaREM = 1;
                    //STATE <= 6;
                end
            end
            3'd6: begin
                cargaREM = 0;
                if(RI == OP_STA) begin
                    cargaRDM = 1;
                end else begin
                    memRead = 1;
                end
                //STATE <= 7;
            end
            3'd7: begin
                cargaRDM = 0;
                if(RI == OP_STA) begin
                    memWrite = 1;
                end else begin
                    cargaAC = 1;
                    cargaNZ = 1;
                    ULA_SEL = RI[2:0];
                end

                //STATE <= 0;
            end
        endcase
    end


endmodule

trace.vcd
$version Generated by VerilatedVcd $end
$date Tue Nov 30 17:18:21 2021
 $end
$timescale  10s $end

 $scope module TOP $end
  $var wire  1 9 i_clk $end
  $var wire  1 : i_rst $end
  $scope module neander $end
   $var wire  8 # ACC [7:0] $end
   $var wire  1 3 N $end
   $var wire  8 > OP_ADD [7:0] $end
   $var wire  8 @ OP_AND [7:0] $end
   $var wire  8 E OP_HLT [7:0] $end
   $var wire  8 B OP_JMP [7:0] $end
   $var wire  8 C OP_JN [7:0] $end
   $var wire  8 D OP_JZ [7:0] $end
   $var wire  8 = OP_LDA [7:0] $end
   $var wire  8 ; OP_NOP [7:0] $end
   $var wire  8 A OP_NOT [7:0] $end
   $var wire  8 ? OP_OR [7:0] $end
   $var wire  8 < OP_STA [7:0] $end
   $var wire  8 & RDM [7:0] $end
   $var wire  8 1 REM [7:0] $end
   $var wire  8 0 RI [7:0] $end
   $var wire  1 2 SEL $end
   $var wire  3 5 STATE [2:0] $end
   $var wire  3 F ULA_ADD [2:0] $end
   $var wire  3 H ULA_AND [2:0] $end
   $var wire  1 ( ULA_N $end
   $var wire  3 I ULA_NOT [2:0] $end
   $var wire  3 G ULA_OR [2:0] $end
   $var wire  8 % ULA_OUT [7:0] $end
   $var wire  3 $ ULA_SEL [2:0] $end
   $var wire  8 & ULA_Y [7:0] $end
   $var wire  1 ' ULA_Z $end
   $var wire  1 4 Z $end
   $var wire  1 ) cargaAC $end
   $var wire  1 * cargaNZ $end
   $var wire  1 7 cargaPC $end
   $var wire  8 & cargaPC_val [7:0] $end
   $var wire  1 , cargaRDM $end
   $var wire  1 + cargaREM $end
   $var wire  1 - cargaRI $end
   $var wire  1 9 i_clk $end
   $var wire  1 : i_rst $end
   $var wire  1 8 incrementaPC $end
   $var wire  1 . memRead $end
   $var wire  1 / memWrite $end
   $var wire  8 6 valorPC [7:0] $end
   $scope module PC $end
    $var wire  1 9 i_clk $end
    $var wire  1 8 i_inc $end
    $var wire  8 & i_preload [7:0] $end
    $var wire  1 7 i_preload_s $end
    $var wire  1 : i_rst $end
    $var wire  8 6 internal_PC [7:0] $end
    $var wire  8 6 o_PC [7:0] $end
   $upscope $end
   $scope module ula $end
    $var wire  3 F ADD [2:0] $end
    $var wire  3 H AND [2:0] $end
    $var wire  3 I NOT [2:0] $end
    $var wire  3 G OR [2:0] $end
    $var wire  8 # i_A [7:0] $end
    $var wire  8 & i_B [7:0] $end
    $var wire  3 $ i_SEL [2:0] $end
    $var wire  1 ( o_NEG $end
    $var wire  8 % o_OUT [7:0] $end
    $var wire  1 ' o_ZERO $end
   $upscope $end
  $upscope $end
 $upscope $end
$enddefinitions $end


#0
b00000000 #
b000 $
b00000000 %
b00000000 &
1'
0(
0)
0*
1+
0,
0-
0.
0/
b00000000 0
b00000000 1
02
03
04
b000 5
b00000000 6
07
08
09
1:
b00000000 ;
b00000001 <
b00000010 =
b00000011 >
b00000100 ?
b00000101 @
b00000110 A
b00001000 B
b00001001 C
b00001010 D
b00001111 E
b011 F
b100 G
b101 H
b110 I
#1
0+
1.
b001 5
18
0:
#2
b00000010 %
b00000010 &
0'
1-
0.
b010 5
b00000001 6
08
#3
1+
0-
b00000010 0
b011 5
#4
0+
1.
b00000001 1
b100 5
18
#5
b10000000 %
b10000000 &
1(
1+
12
b101 5
b00000010 6
08
#6
0+
b10000000 1
b110 5
#7
b010 $
b01100111 %
b01100111 &
0(
1)
1*
b111 5
#8
b01100111 #
0)
0*
1+
0.
02
b000 5
#9
0+
1.
b00000010 1
b001 5
18
#10
b00001111 %
b00001111 &
1-
0.
b010 5
b00000011 6
08
#11
1+
0-
b00001111 0
b011 5
#12
b00000011 1
b000 5
#13
b00000000 6
1:
#14
0+
1.
b00000000 1
b001 5
18
0:
#15
b00000010 %
b00000010 &
1-
0.
b010 5
b00000001 6
08
#16
1+
0-
b00000010 0
b011 5
#17
0+
1.
b00000001 1
b100 5
18
#18
b10000000 %
b10000000 &
1(
1+
12
b101 5
b00000010 6
08
#19
0+
b10000000 1
b110 5
#20
b11000110 %
b11000110 &
1)
1*
b111 5
#21
b11000110 #
0)
0*
1+
0.
02
13
b000 5
#22
0+
1.
b00000010 1
b001 5
18
#23
b00000001 %
b00000001 &
0(
1-
0.
b010 5
b00000011 6
08
#24
1+
0-
b00000001 0
b011 5
#25
0+
1.
b00000011 1
b100 5
18
#26
b10000001 %
b10000001 &
1(
1+
12
b101 5
b00000100 6
08
#27
0+
1,
b10000001 1
b110 5
#28
b11000110 %
b11000110 &
0,
1/
b111 5
#29
b00000000 %
b00000000 &
1'
0(
1+
0.
0/
02
b000 5
#30
0+
1.
b00000100 1
b001 5
18
#31
b00001111 %
b00001111 &
0'
1-
0.
b010 5
b00000101 6
08
#32
1+
0-
b00001111 0
b011 5
#33
b00000101 1
b000 5
#34
b00000000 6
1:
#35
0+
1.
b00000000 1
b001 5
18
0:
#36
b00000010 %
b00000010 &
1-
0.
b010 5
b00000001 6
08
#37
1+
0-
b00000010 0
b011 5
#38
0+
1.
b00000001 1
b100 5
18
#39
b10000000 %
b10000000 &
1(
1+
12
b101 5
b00000010 6
08
#40
0+
b10000000 1
b110 5
#41
b01101001 %
b01101001 &
0(
1)
1*
b111 5
#42
b01101001 #
0)
0*
1+
0.
02
03
b000 5
#43
0+
1.
b00000010 1
b001 5
18
#44
b00000011 %
b00000011 &
1-
0.
b010 5
b00000011 6
08
#45
1+
0-
b00000011 0
b011 5
#46
0+
1.
b00000011 1
b100 5
18
#47
b10000001 %
b10000001 &
1(
1+
12
b101 5
b00000100 6
08
#48
0+
b10000001 1
b110 5
#49
b011 $
b11011100 %
b01110011 &
1)
1*
b111 5
#50
b11011100 #
b01001111 %
0(
0)
0*
1+
0.
02
13
b000 5
#51
0+
1.
b00000100 1
b001 5
18
#52
b11101011 %
b00001111 &
1(
1-
0.
b010 5
b00000101 6
08
#53
1+
0-
b00001111 0
b011 5
#54
b00000101 1
b000 5
#55
b00000000 6
1:
#56
0+
1.
b00000000 1
b001 5
18
0:
#57
b11011110 %
b00000010 &
1-
0.
b010 5
b00000001 6
08
#58
1+
0-
b00000010 0
b011 5
#59
0+
1.
b00000001 1
b100 5
18
#60
b01011100 %
b10000000 &
0(
1+
12
b101 5
b00000010 6
08
#61
0+
b10000000 1
b110 5
#62
b010 $
b01010001 %
b01010001 &
1)
1*
b111 5
#63
b01010001 #
0)
0*
1+
0.
02
03
b000 5
#64
0+
1.
b00000010 1
b001 5
18
#65
b00000101 %
b00000101 &
1-
0.
b010 5
b00000011 6
08
#66
1+
0-
b00000101 0
b011 5
#67
0+
1.
b00000011 1
b100 5
18
#68
b10000001 %
b10000001 &
1(
1+
12
b101 5
b00000100 6
08
#69
0+
b10000001 1
b110 5
#70
b101 $
b01010001 %
b11111111 &
0(
1)
1*
b111 5
#71
0)
0*
1+
0.
02
b000 5
#72
0+
1.
b00000100 1
b001 5
18
#73
b00000001 %
b00001111 &
1-
0.
b010 5
b00000101 6
08
#74
1+
0-
b00001111 0
b011 5
#75
b00000101 1
b000 5
#76
b00000000 6
1:
#77
0+
1.
b00000000 1
b001 5
18
0:
#78
b00000000 %
b00000010 &
1'
1-
0.
b010 5
b00000001 6
08
#79
1+
0-
b00000010 0
b011 5
#80
0+
1.
b00000001 1
b100 5
18
#81
b10000000 &
1+
12
b101 5
b00000010 6
08
#82
0+
b10000000 1
b110 5
#83
b010 $
b01001010 %
b01001010 &
0'
1)
1*
b111 5
#84
b01001010 #
0)
0*
1+
0.
02
b000 5
#85
0+
1.
b00000010 1
b001 5
18
#86
b00000100 %
b00000100 &
1-
0.
b010 5
b00000011 6
08
#87
1+
0-
b00000100 0
b011 5
#88
0+
1.
b00000011 1
b100 5
18
#89
b10000001 %
b10000001 &
1(
1+
12
b101 5
b00000100 6
08
#90
0+
b10000001 1
b110 5
#91
b100 $
b11101110 %
b11101100 &
1)
1*
b111 5
#92
b11101110 #
0)
0*
1+
0.
02
13
b000 5
#93
0+
1.
b00000100 1
b001 5
18
#94
b11101111 %
b00001111 &
1-
0.
b010 5
b00000101 6
08
#95
1+
0-
b00001111 0
b011 5
#96
b00000101 1
b000 5
#97
b00000000 6
1:
#98
0+
1.
b00000000 1
b001 5
18
0:
#99
b11101110 %
b00000010 &
1-
0.
b010 5
b00000001 6
08
#100
1+
0-
b00000010 0
b011 5
#101
0+
1.
b00000001 1
b100 5
18
#102
b10000000 &
1+
12
b101 5
b00000010 6
08
#103
0+
b10000000 1
b110 5
#104
b010 $
b00101001 %
b00101001 &
0(
1)
1*
b111 5
#105
b00101001 #
0)
0*
1+
0.
02
03
b000 5
#106
0+
1.
b00000010 1
b001 5
18
#107
b00000110 %
b00000110 &
1-
0.
b010 5
b00000011 6
08
#108
b110 $
b11010110 %
1(
1)
1*
0-
b00000110 0
b011 5
#109
b11010110 #
b00101001 %
0(
0)
0*
1+
13
b000 5
#110
0+
1.
b00000011 1
b001 5
18
#111
b00001111 &
1-
0.
b010 5
b00000100 6
08
#112
1+
0-
b00001111 0
b011 5
#113
b00000100 1
b000 5
#114
b00000000 6
1:
#115
0+
1.
b00000000 1
b001 5
18
0:
#116
b00001000 &
1-
0.
b010 5
b00000001 6
08
#117
1+
0-
b00001000 0
b011 5
#118
0+
1.
b00000001 1
b100 5
#119
b10000000 &
b101 5
17
#120
1+
0.
b000 5
b10000000 6
07
#121
0+
1.
b10000000 1
b001 5
18
#122
b00001111 &
1-
0.
b010 5
b10000001 6
08
#123
1+
0-
b00001111 0
b011 5
#124
b10000001 1
b000 5
#125
b00000000 6
1:
#126
0+
1.
b00000000 1
b001 5
18
0:
#127
b00000010 &
1-
0.
b010 5
b00000001 6
08
#128
1+
0-
b00000010 0
b011 5
#129
0+
1.
b00000001 1
b100 5
18
#130
b10000000 &
1+
12
b101 5
b00000010 6
08
#131
0+
b10000000 1
b110 5
#132
b010 $
b00000101 %
b00000101 &
1)
1*
b111 5
#133
b00000101 #
0)
0*
1+
0.
02
03
b000 5
#134
0+
1.
b00000010 1
b001 5
18
#135
b00001001 %
b00001001 &
1-
0.
b010 5
b00000011 6
08
#136
0-
b00001001 0
b011 5
18
#137
1+
b000 5
b00000100 6
08
#138
0+
1.
b00000100 1
b001 5
18
#139
b00001111 %
b00001111 &
1-
0.
b010 5
b00000101 6
08
#140
1+
0-
b00001111 0
b011 5
#141
b00000101 1
b000 5
#142
b00000000 6
1:
#143
0+
1.
b00000000 1
b001 5
18
0:
#144
b00000010 %
b00000010 &
1-
0.
b010 5
b00000001 6
08
#145
1+
0-
b00000010 0
b011 5
#146
0+
1.
b00000001 1
b100 5
18
#147
b10000000 %
b10000000 &
1(
1+
12
b101 5
b00000010 6
08
#148
0+
b10000000 1
b110 5
#149
b11110111 %
b11110111 &
1)
1*
b111 5
#150
b11110111 #
0)
0*
1+
0.
02
13
b000 5
#151
0+
1.
b00000010 1
b001 5
18
#152
b00001001 %
b00001001 &
0(
1-
0.
b010 5
b00000011 6
08
#153
1+
0-
b00001001 0
b011 5
#154
0+
1.
b00000011 1
b100 5
#155
b10000001 %
b10000001 &
1(
b101 5
17
#156
1+
0.
b000 5
b10000001 6
07
#157
0+
1.
b10000001 1
b001 5
18
#158
b00001111 %
b00001111 &
0(
1-
0.
b010 5
b10000010 6
08
#159
1+
0-
b00001111 0
b011 5
#160
b10000010 1
b000 5
#161
b00000000 6
1:
#162
0+
1.
b00000000 1
b001 5
18
0:
#163
b00000010 %
b00000010 &
1-
0.
b010 5
b00000001 6
08
#164
1+
0-
b00000010 0
b011 5
#165
0+
1.
b00000001 1
b100 5
18
#166
b10000000 %
b10000000 &
1(
1+
12
b101 5
b00000010 6
08
#167
0+
b10000000 1
b110 5
#168
b00000101 %
b00000101 &
0(
1)
1*
b111 5
#169
b00000101 #
0)
0*
1+
0.
02
03
b000 5
#170
0+
1.
b00000010 1
b001 5
18
#171
b00001010 %
b00001010 &
1-
0.
b010 5
b00000011 6
08
#172
0-
b00001010 0
b011 5
18
#173
1+
b000 5
b00000100 6
08
#174
0+
1.
b00000100 1
b001 5
18
#175
b00001111 %
b00001111 &
1-
0.
b010 5
b00000101 6
08
#176
1+
0-
b00001111 0
b011 5
#177
b00000101 1
b000 5
#178
b00000000 6
1:
#179
0+
1.
b00000000 1
b001 5
18
0:
#180
b00000010 %
b00000010 &
1-
0.
b010 5
b00000001 6
08
#181
1+
0-
b00000010 0
b011 5
#182
0+
1.
b00000001 1
b100 5
18
#183
b10000000 %
b10000000 &
1(
1+
12
b101 5
b00000010 6
08
#184
0+
b10000000 1
b110 5
#185
b00000000 %
b00000000 &
1'
0(
1)
1*
b111 5
#186
b00000000 #
0)
0*
1+
0.
02
14
b000 5
#187
0+
1.
b00000010 1
b001 5
18
#188
b00001010 %
b00001010 &
0'
1-
0.
b010 5
b00000011 6
08
#189
1+
0-
b00001010 0
b011 5
#190
0+
1.
b00000011 1
b100 5
#191
b10000001 %
b10000001 &
1(
b101 5
17
#192
1+
0.
b000 5
b10000001 6
07
#193
0+
1.
b10000001 1
b001 5
18
#194
b00001111 %
b00001111 &
0(
1-
0.
b010 5
b10000010 6
08
#195
1+
0-
b00001111 0
b011 5
#196
b10000010 1
b000 5
